x_ipe/__init__.py
x_ipe/__main__.py
x_ipe/app.py
x_ipe/config.py
x_ipe/cli/__init__.py
x_ipe/cli/main.py
x_ipe/core/__init__.py
x_ipe/core/config.py
x_ipe/core/hashing.py
x_ipe/core/paths.py
x_ipe/core/scaffold.py
x_ipe/core/skills.py
x_ipe/handlers/__init__.py
x_ipe/handlers/terminal_handlers.py
x_ipe/handlers/voice_handlers.py
x_ipe/resources/config/.env.example
x_ipe/resources/config/copilot-prompt.json
x_ipe/resources/config/tools.json
x_ipe/resources/copilot/mcp-config.json
x_ipe/resources/planning/features.md
x_ipe/resources/planning/task-board.md
x_ipe/resources/themes/theme-default/component-visualization.html
x_ipe/resources/themes/theme-default/design-system.md
x_ipe/routes/__init__.py
x_ipe/routes/ideas_routes.py
x_ipe/routes/main_routes.py
x_ipe/routes/project_routes.py
x_ipe/routes/proxy_routes.py
x_ipe/routes/settings_routes.py
x_ipe/routes/tools_routes.py
x_ipe/routes/uiux_feedback_routes.py
x_ipe/services/__init__.py
x_ipe/services/config_service.py
x_ipe/services/file_service.py
x_ipe/services/ideas_service.py
x_ipe/services/proxy_service.py
x_ipe/services/settings_service.py
x_ipe/services/skills_service.py
x_ipe/services/terminal_service.py
x_ipe/services/themes_service.py
x_ipe/services/tools_config_service.py
x_ipe/services/uiux_feedback_service.py
x_ipe/services/voice_input_service_v2.py
x_ipe/static/3rdparty/html2canvas.min.js
x_ipe/static/3rdparty/css/bootstrap-icons.css
x_ipe/static/3rdparty/css/bootstrap.min.css
x_ipe/static/3rdparty/css/codemirror-dialog.min.css
x_ipe/static/3rdparty/css/codemirror.min.css
x_ipe/static/3rdparty/css/easymde.min.css
x_ipe/static/3rdparty/css/highlight-github.min.css
x_ipe/static/3rdparty/css/xterm.css
x_ipe/static/3rdparty/fonts/bootstrap-icons.woff
x_ipe/static/3rdparty/fonts/bootstrap-icons.woff2
x_ipe/static/3rdparty/js/bootstrap.bundle.min.js
x_ipe/static/3rdparty/js/codemirror-dialog.min.js
x_ipe/static/3rdparty/js/codemirror-jump-to-line.min.js
x_ipe/static/3rdparty/js/codemirror-search.min.js
x_ipe-1.0.24.dist-info/METADATA
x_ipe-1.0.24.dist-info/WHEEL
x_ipe-1.0.24.dist-info/entry_points.txt
x_ipe-1.0.24.dist-info/licenses/LICENSE
x_ipe-1.0.24.dist-info/RECORD
