Metadata-Version: 2.4
Name: x-ipe
Version: 1.0.24
Summary: X-IPE: AI-powered development framework
License-File: LICENSE
Requires-Python: >=3.12
Requires-Dist: beautifulsoup4>=4.14.3
Requires-Dist: click>=8.1.0
Requires-Dist: dashscope>=1.25.9
Requires-Dist: eventlet>=0.40.4
Requires-Dist: flask-socketio>=5.6.0
Requires-Dist: flask>=3.1.2
Requires-Dist: gevent-websocket>=0.10.1
Requires-Dist: gevent>=25.9.1
Requires-Dist: pillow>=12.1.0
Requires-Dist: ptyprocess>=0.7.0
Requires-Dist: python-socketio>=5.16.0
Requires-Dist: pyyaml>=6.0.3
Requires-Dist: requests>=2.32.5
Requires-Dist: watchdog>=6.0.0
Requires-Dist: websockets>=16.0
